pydantic_settings_aws/__init__.py
pydantic_settings_aws/aws.py
pydantic_settings_aws/logger.py
pydantic_settings_aws/models.py
pydantic_settings_aws/py.typed
pydantic_settings_aws/settings.py
pydantic_settings_aws/sources.py
pydantic_settings_aws/utils.py
pydantic_settings_aws/version.py
pydantic_settings_aws-0.1.2.dist-info/METADATA
pydantic_settings_aws-0.1.2.dist-info/WHEEL
pydantic_settings_aws-0.1.2.dist-info/licenses/LICENSE
pydantic_settings_aws-0.1.2.dist-info/RECORD
