Metadata-Version: 2.4
Name: pydantic-settings-aws
Version: 0.1.2
Summary: Settings management using AWS Secrets Manager and Pydantic
Project-URL: Homepage, https://github.com/ceb10n/pydantic-settings-aws
Project-URL: Documentation, https://ceb10n.github.io/pydantic-settings-aws/
Project-URL: Repository, https://github.com/ceb10n/pydantic-settings-aws
Author-email: Rafael de Oliveira Marques <rafaelomarques@gmail.com>
License-Expression: MIT
License-File: LICENSE
Classifier: Development Status :: 3 - Alpha
Classifier: Environment :: Console
Classifier: Intended Audience :: Developers
Classifier: Intended Audience :: Information Technology
Classifier: Intended Audience :: System Administrators
Classifier: License :: OSI Approved :: MIT License
Classifier: Operating System :: MacOS
Classifier: Operating System :: Microsoft
Classifier: Operating System :: POSIX :: Linux
Classifier: Operating System :: Unix
Classifier: Programming Language :: Python
Classifier: Programming Language :: Python :: 3
Classifier: Programming Language :: Python :: 3 :: Only
Classifier: Programming Language :: Python :: 3.8
Classifier: Programming Language :: Python :: 3.9
Classifier: Programming Language :: Python :: 3.10
Classifier: Programming Language :: Python :: 3.11
Classifier: Programming Language :: Python :: 3.12
Classifier: Programming Language :: Python :: 3.13
Classifier: Programming Language :: Python :: 3.14
Classifier: Topic :: Internet
Classifier: Topic :: Software Development :: Libraries :: Python Modules
Requires-Python: >=3.8
Requires-Dist: boto3>=1.27.0
Requires-Dist: pydantic-settings>=2.0.2
Requires-Dist: pydantic>=2.0.1
